msticnb/__init__.py
msticnb/_version.py
msticnb/class_doc.py
msticnb/common.py
msticnb/data_providers.py
msticnb/data_viewers.py
msticnb/nb_browser.py
msticnb/nb_metadata.py
msticnb/nb_pivot.py
msticnb/notebooklet.py
msticnb/notebooklet_result.py
msticnb/options.py
msticnb/read_modules.py
msticnb/template.py
msticnb/nb/__init__.py
msticnb/nb/azsent/__init__.py
msticnb/nb/azsent/account/__init__.py
msticnb/nb/azsent/account/account_summary.py
msticnb/nb/azsent/account/account_summary.yaml
msticnb/nb/azsent/alert/__init__.py
msticnb/nb/azsent/alert/ti_enrich.py
msticnb/nb/azsent/alert/ti_enrich.yaml
msticnb/nb/azsent/host/__init__.py
msticnb/nb/azsent/host/host_logons_summary.py
msticnb/nb/azsent/host/host_logons_summary.yaml
msticnb/nb/azsent/host/host_network_summary.py
msticnb/nb/azsent/host/host_network_summary.yaml
msticnb/nb/azsent/host/host_summary.py
msticnb/nb/azsent/host/host_summary.yaml
msticnb/nb/azsent/host/logon_session_rarity.py
msticnb/nb/azsent/host/logon_session_rarity.yaml
msticnb/nb/azsent/host/win_host_events.py
msticnb/nb/azsent/host/win_host_events.yaml
msticnb/nb/azsent/network/__init__.py
msticnb/nb/azsent/network/ip_summary.py
msticnb/nb/azsent/network/ip_summary.yaml
msticnb/nb/azsent/network/network_flow_summary.py
msticnb/nb/azsent/network/network_flow_summary.yaml
msticnb/nb/azsent/url/__init__.py
msticnb/nb/azsent/url/url_summary.py
msticnb/nb/azsent/url/url_summary.yaml
msticnb/nb/template/__init__.py
msticnb/nb/template/nb_template.py
msticnb/nb/template/nb_template.yaml
msticnb/nblib/__init__.py
msticnb/nblib/entity_tools.py
msticnb/nblib/iptools.py
msticnb/nblib/ti.py
msticnb/nblib/azsent/__init__.py
msticnb/nblib/azsent/alert.py
msticnb/nblib/azsent/host.py
msticnb-1.2.3.dist-info/LICENSE
msticnb-1.2.3.dist-info/METADATA
msticnb-1.2.3.dist-info/WHEEL
msticnb-1.2.3.dist-info/top_level.txt
msticnb-1.2.3.dist-info/RECORD
