Metadata-Version: 2.1
Name: msticnb
Version: 1.2.3
Summary: MSTIC Notebooklets
Home-page: https://github.com/microsoft/msticnb
Author: Ian Hellen
Author-email: ianhelle@microsoft.com
License: MIT License
Project-URL: Documentation, https://msticnb.readthedocs.io
Project-URL: Code, https://github.com/microsoft/msticnb
Keywords: security,cybersecurity,infosec,jupyter,notebook,azure,sentinel
Classifier: Programming Language :: Python :: 3.6
Classifier: License :: OSI Approved :: MIT License
Classifier: Operating System :: OS Independent
Classifier: Development Status :: 4 - Beta
Requires-Python: >=3.6
License-File: LICENSE
Requires-Dist: bokeh<3.4.0,>=1.4.0
Requires-Dist: defusedxml>=0.6.0
Requires-Dist: ipython>=7.23.1
Requires-Dist: ipywidgets>=7.5.1
Requires-Dist: lxml>=4.4.2
Requires-Dist: Markdown>=3.2.1
Requires-Dist: msticpy[azure]>=2.3.1
Requires-Dist: numpy>=1.17.3
Requires-Dist: packaging>=19.2
Requires-Dist: pandas>=0.25.3
Requires-Dist: python-dateutil>=2.8.1
Requires-Dist: tqdm>=4.41.1
Requires-Dist: python-whois>=0.7.3
Requires-Dist: tldextract>=4.0.0
